<?xml version="1.0" encoding="UTF-8"?>
<gresources>
  <gresource prefix="/org/gnome/Builder">
    <file compressed="true">data/ui/gb-application-menu.ui</file>
    <file compressed="true">data/ui/gb-tree-menu.ui</file>
    <file compressed="true">data/style-schemes/solarized-dark.xml</file>
    <file compressed="true">data/style-schemes/solarized-light.xml</file>
    <file compressed="false">data/icons/class-16x.png</file>
    <file compressed="false">data/icons/deprecated-16x.png</file>
    <file compressed="false">data/icons/enum-16x.png</file>
    <file compressed="false">data/icons/enum-value-16x.png</file>
    <file compressed="false">data/icons/keyword-16x.png</file>
    <file compressed="false">data/icons/method-16x.png</file>
    <file compressed="false">data/icons/static-16x.png</file>
    <file compressed="false">data/icons/template-16x.png</file>
  </gresource>
</gresources>
